taxpr/__init__.py
taxpr/dfg.py
taxpr/primitives.py
taxpr/util.py
taxpr-0.0.1.dist-info/licenses/LICENSE
taxpr-0.0.1.dist-info/METADATA
taxpr-0.0.1.dist-info/WHEEL
taxpr-0.0.1.dist-info/top_level.txt
taxpr-0.0.1.dist-info/RECORD
