Metadata-Version: 2.4
Name: taxpr
Version: 0.0.1
Summary: A small example package
Author: Oscar Toomey
License-Expression: MIT
Project-URL: Homepage, https://github.com/otoomey/taxpr
Project-URL: Issues, https://github.com/otoomey/taxpr/issues
Classifier: Programming Language :: Python :: 3
Classifier: Operating System :: OS Independent
Requires-Python: >=3.13
License-File: LICENSE
Requires-Dist: jax>=0.8.0
Requires-Dist: jaxtyping>=0.2.20
Provides-Extra: dev
Requires-Dist: pre-commit; extra == "dev"
Provides-Extra: docs
Requires-Dist: zensical==0.0.11; extra == "docs"
Requires-Dist: mkdocstrings-python==2.0.1; extra == "docs"
Provides-Extra: tests
Requires-Dist: jaxlib; extra == "tests"
Requires-Dist: pytest; extra == "tests"
Dynamic: license-file
